bedrock_agent/__init__.py
bedrock_agent/py.typed
bedrock_agent/_jsii/__init__.py
bedrock_agent/_jsii/bedrock-agents-cdk@0.0.11.jsii.tgz
bedrock_agent-0.0.11.dist-info/LICENSE
bedrock_agent-0.0.11.dist-info/METADATA
bedrock_agent-0.0.11.dist-info/WHEEL
bedrock_agent-0.0.11.dist-info/top_level.txt
bedrock_agent-0.0.11.dist-info/RECORD
